hparams/__init__.py
hparams/params.py
utils/__init__.py
utils/branch.py
utils/concurrent.py
utils/convolution_config.py
utils/functions.py
utils/repeated.py
torchinceptionresnetv2-0.0.4.dist-info/LICENSE
torchinceptionresnetv2-0.0.4.dist-info/METADATA
torchinceptionresnetv2-0.0.4.dist-info/WHEEL
torchinceptionresnetv2-0.0.4.dist-info/top_level.txt
torchinceptionresnetv2-0.0.4.dist-info/RECORD
